[
  {
    "year": 2019,
    "quarter": 4,
    "cresRec": 0.237656564,
    "divBruta": 1297285000,
    "data": "12/31/2019 00:00:00",
    "qntAcoes": 357547200,
    "cotacao": 12.02,
    "pl": 203.881912,
    "pvp": 8.538777,
    "pebit": 79.437294,
    "pfco": 87.24279,
    "psr": 18.8131943,
    "pAtivos": 3.015879,
    "pCapGiro": 82.2268753,
    "pAtivCLiq": -6.074499,
    "divYeld": 0,
    "evebit": 95.02683,
    "valordaFirma": 12840025100,
    "valordeMercado": 10733567000,
    "fci": 28233000,
    "dbPl": 0,
    "vpa": 3.51572585,
    "margBruta": 0.564406335,
    "capex": 70333000,
    "margLiq": 0.09227496,
    "capexLL": 1.335961,
    "giroAtivos": 0.160306573,
    "fcf": 99455000,
    "caixaLivre": -0.536280036,
    "fcl": -4657000,
    "payout": 0,
    "lpa": 0.1472421,
    "margEbit": 0.236830756,
    "roic": 0,
    "ebitAtivo": 0.03796553,
    "fco": 123031000,
    "dpa": 0,
    "liqCorrent": 1.32274461,
    "divBrPatrim": 1.03201735,
    "capexFco": 0.5716689,
    "fct": 0,
    "ativoCirculante": 534992000,
    "fciLL": -0.536280036,
    "capexDetails": 0,
    "roe": 0.041880995,
    "roa": 0.0147922821,
    "dlpl": 0.8764755,
    "payoutDetails": 0,
    "ebit": 135120000,
    "lucroLiquido": 52646000,
    "receitaLiquida": 570534000
  },
  {
    "year": 2019,
    "quarter": 3,
    "cresRec": 0.07621899,
    "divBruta": 1291835000,
    "data": "09/30/2019 00:00:00",
    "qntAcoes": 357547200,
    "cotacao": 12.02,
    "pl": 742.807434,
    "pvp": 8.123779,
    "pebit": 265.972046,
    "pfco": 146.090591,
    "psr": 40.29132,
    "pAtivos": 3.0423038,
    "pCapGiro": 42.23021,
    "pAtivCLiq": -6.53315449,
    "divYeld": 0,
    "evebit": 314.6548,
    "valordaFirma": 12698208300,
    "valordeMercado": 10733567000,
    "fci": 104125000,
    "dbPl": 0,
    "vpa": 3.69532442,
    "margBruta": 0.4968487,
    "capex": 77866000,
    "margLiq": 0.0542419441,
    "capexLL": 5.38865042,
    "giroAtivos": 0.07550767,
    "fcf": -34955000,
    "caixaLivre": -7.20588255,
    "fcl": 4302000,
    "payout": 0,
    "lpa": 0.0404142439,
    "margEbit": 0.151487052,
    "roic": 0,
    "ebitAtivo": 0.0114384349,
    "fco": 73472000,
    "dpa": 0,
    "liqCorrent": 1.82056916,
    "divBrPatrim": 0.977734745,
    "capexFco": 1.05980515,
    "fct": 0,
    "ativoCirculante": 563914000,
    "fciLL": -7.20588255,
    "capexDetails": 0,
    "roe": 0.010936588,
    "roa": 0.004095683,
    "dlpl": 0.7944156,
    "payoutDetails": 0,
    "ebit": 40356000,
    "lucroLiquido": 14450000,
    "receitaLiquida": 266399000
  },
  {
    "year": 2019,
    "quarter": 2,
    "cresRec": -1,
    "divBruta": 1256880000,
    "data": "06/30/2019 00:00:00",
    "qntAcoes": 357547200,
    "cotacao": 12.02,
    "pl": 0,
    "pvp": 8.213608,
    "pebit": 0,
    "pfco": 773.9809,
    "psr": 0,
    "pAtivos": 3.086329,
    "pCapGiro": 42.18639,
    "pAtivCLiq": -6.59318542,
    "divYeld": 0,
    "evebit": 0,
    "valordaFirma": 12694436900,
    "valordeMercado": 10733567000,
    "fci": 121519000,
    "dbPl": 0,
    "vpa": 3.65491033,
    "margBruta": 0,
    "capex": 68712000,
    "margLiq": 0,
    "capexLL": 0,
    "giroAtivos": 0,
    "fcf": -109700000,
    "caixaLivre": 0,
    "fcl": 2049000,
    "payout": 0,
    "lpa": 0,
    "margEbit": 0,
    "roic": 0,
    "ebitAtivo": 0,
    "fco": 13868000,
    "dpa": 0,
    "liqCorrent": 1.8817178,
    "divBrPatrim": 0.9617976,
    "capexFco": 4.95471573,
    "fct": 0,
    "ativoCirculante": 542996000,
    "fciLL": 0,
    "capexDetails": 0,
    "roe": 0,
    "roa": 0,
    "dlpl": 0.801018953,
    "payoutDetails": 0,
    "ebit": 0,
    "lucroLiquido": 0,
    "receitaLiquida": 0
  },
  {
    "year": 2019,
    "quarter": 1,
    "cresRec": 0.08800317,
    "divBruta": 1147180000,
    "data": "03/31/2019 00:00:00",
    "qntAcoes": 357547200,
    "cotacao": 12.02,
    "pl": 136.179321,
    "pvp": 5.514938,
    "pebit": 74.76194,
    "pfco": 97.0666,
    "psr": 24.9456463,
    "pAtivos": 2.13145471,
    "pCapGiro": -99.98424,
    "pAtivCLiq": -4.45308,
    "divYeld": 0,
    "evebit": 95.0138,
    "valordaFirma": 9101657000,
    "valordeMercado": 7161670660,
    "fci": 62587000,
    "dbPl": 0,
    "vpa": 3.631954,
    "margBruta": 0.5737554,
    "capex": 28160000,
    "margLiq": 0.183182329,
    "capexLL": 0.535463035,
    "giroAtivos": 0.08544395,
    "fcf": 11777000,
    "caixaLivre": -1.19009316,
    "fcl": -583000,
    "payout": 0,
    "lpa": 0.147085473,
    "margEbit": 0.333667725,
    "roic": 0,
    "ebitAtivo": 0.0285098888,
    "fco": 73781000,
    "dpa": 0,
    "liqCorrent": 0.863507,
    "divBrPatrim": 0.8834009,
    "capexFco": 0.3816701,
    "fct": 0,
    "ativoCirculante": 453146000,
    "fciLL": -1.19009316,
    "capexDetails": 0,
    "roe": 0.0404976159,
    "roa": 0.0156518221,
    "dlpl": 0.7899068,
    "payoutDetails": 0,
    "ebit": 95793000,
    "lucroLiquido": 52590000,
    "receitaLiquida": 287091000
  },
  {
    "year": 2018,
    "quarter": 4,
    "cresRec": 0.25575608,
    "divBruta": 1158880000,
    "data": "12/31/2018 00:00:00",
    "qntAcoes": 357547200,
    "cotacao": 12.02,
    "pl": -83.1853,
    "pvp": 5.74448156,
    "pebit": -81.07022,
    "pfco": -166.13121,
    "psr": 13.0962248,
    "pAtivos": 2.15158367,
    "pCapGiro": -113.406349,
    "pAtivCLiq": -4.30032873,
    "divYeld": 0,
    "evebit": -103.642273,
    "valordaFirma": 9151094000,
    "valordeMercado": 7158095360,
    "fci": 27111000,
    "dbPl": 0,
    "vpa": 3.48508382,
    "margBruta": 0.563840032,
    "capex": 30265000,
    "margLiq": -0.157434359,
    "capexLL": -0.351714134,
    "giroAtivos": 0.164290383,
    "fcf": -70972000,
    "caixaLivre": 0.315061,
    "fcl": 774000,
    "payout": -0.0355142355,
    "lpa": -0.240667522,
    "margEbit": -0.161541745,
    "roic": 0,
    "ebitAtivo": -0.0265397541,
    "fco": -43087000,
    "dpa": 0,
    "liqCorrent": 0.868333936,
    "divBrPatrim": 0.9300191,
    "capexFco": -0.702416062,
    "fct": 0,
    "ativoCirculante": 416268000,
    "fciLL": 0.315061,
    "capexDetails": 0,
    "roe": -0.06905645,
    "roa": -0.0258649513,
    "dlpl": 0.8595462,
    "payoutDetails": 0,
    "ebit": -88295000,
    "lucroLiquido": -86050000,
    "receitaLiquida": 546577000
  },
  {
    "year": 2018,
    "quarter": 3,
    "cresRec": 0.09491224,
    "divBruta": 1143492000,
    "data": "09/30/2018 00:00:00",
    "qntAcoes": 357547200,
    "cotacao": 12.02,
    "pl": -1965.42981,
    "pvp": 6.19258976,
    "pebit": 206.511322,
    "pfco": 185.476517,
    "psr": 27.4947586,
    "pAtivos": 2.19106364,
    "pCapGiro": 978.9518,
    "pAtivCLiq": -4.237962,
    "divYeld": 0,
    "evebit": 265.084534,
    "valordaFirma": 9188360000,
    "valordeMercado": 7158095360,
    "fci": 30180000,
    "dbPl": 0,
    "vpa": 3.232896,
    "margBruta": 0.5261116,
    "capex": 54530000,
    "margLiq": -0.0139891831,
    "capexLL": -14.9725428,
    "giroAtivos": 0.07969023,
    "fcf": 10898000,
    "caixaLivre": 8.286655,
    "fcl": -2485000,
    "payout": 0,
    "lpa": -0.0101860669,
    "margEbit": 0.133139238,
    "roic": 0,
    "ebitAtivo": 0.0106098959,
    "fco": 38593000,
    "dpa": 0,
    "liqCorrent": 1.01763272,
    "divBrPatrim": 0.989254355,
    "capexFco": 1.41295052,
    "fct": 0,
    "ativoCirculante": 421995000,
    "fciLL": 8.286655,
    "capexDetails": 0,
    "roe": -0.00315075624,
    "roa": -0.00111480127,
    "dlpl": 0.919377148,
    "payoutDetails": 0,
    "ebit": 34662000,
    "lucroLiquido": -3642000,
    "receitaLiquida": 260344000
  },
  {
    "year": 2018,
    "quarter": 2,
    "cresRec": -1,
    "divBruta": 1154390000,
    "data": "06/30/2018 00:00:00",
    "qntAcoes": 357547200,
    "cotacao": 12,
    "pl": 0,
    "pvp": 6.166973,
    "pebit": 0,
    "pfco": 429.073822,
    "psr": 0,
    "pAtivos": 2.18861,
    "pCapGiro": 169.517929,
    "pAtivCLiq": -4.33390045,
    "divYeld": 0,
    "evebit": 0,
    "valordaFirma": 9154993000,
    "valordeMercado": 7150944000,
    "fci": 12362000,
    "dbPl": 0,
    "vpa": 3.24308228,
    "margBruta": 0,
    "capex": 103534000,
    "margLiq": 0,
    "capexLL": 0,
    "giroAtivos": 0,
    "fcf": 238000,
    "caixaLivre": 0,
    "fcl": 4066000,
    "payout": 0,
    "lpa": 0,
    "margEbit": 0,
    "roic": 0,
    "ebitAtivo": 0,
    "fco": 16666000,
    "dpa": 0,
    "liqCorrent": 1.10150051,
    "divBrPatrim": 0.9955457,
    "capexFco": 6.21228838,
    "fct": 0,
    "ativoCirculante": 457788000,
    "fciLL": 0,
    "capexDetails": 0,
    "roe": 0,
    "roa": 0,
    "dlpl": 0.9060795,
    "payoutDetails": 0,
    "ebit": 0,
    "lucroLiquido": 0,
    "receitaLiquida": 0
  },
  {
    "year": 2018,
    "quarter": 1,
    "cresRec": 0.113425426,
    "divBruta": 1154628000,
    "data": "03/31/2018 00:00:00",
    "qntAcoes": 357547200,
    "cotacao": 12,
    "pl": -242.134033,
    "pvp": 5.599212,
    "pebit": -532.3812,
    "pfco": 151.931168,
    "psr": 25.6645679,
    "pAtivos": 2.20280933,
    "pCapGiro": 50.9769478,
    "pAtivCLiq": -4.957516,
    "divYeld": 0.00104573753,
    "evebit": -664.862,
    "valordaFirma": 8930426000,
    "valordeMercado": 7150944000,
    "fci": 44188000,
    "dbPl": 0,
    "vpa": 3.57193112,
    "margBruta": 0.5754636,
    "capex": 50033000,
    "margLiq": -0.105993234,
    "capexLL": -1.69413877,
    "giroAtivos": 0.0858307555,
    "fcf": 7633000,
    "caixaLivre": 1.49622452,
    "fcl": -4754000,
    "payout": 0,
    "lpa": -0.08259888,
    "margEbit": -0.0482071266,
    "roic": 0,
    "ebitAtivo": -0.004137654,
    "fco": 47067000,
    "dpa": 0.01254885,
    "liqCorrent": 1.36301291,
    "divBrPatrim": 0.9040774,
    "capexFco": 1.06301653,
    "fct": 0,
    "ativoCirculante": 526705000,
    "fciLL": 1.49622452,
    "capexDetails": 0,
    "roe": -0.0231244341,
    "roa": -0.009097479,
    "dlpl": 0.7555668,
    "payoutDetails": 0,
    "ebit": -13432000,
    "lucroLiquido": -29533000,
    "receitaLiquida": 278631000
  },
  {
    "year": 2017,
    "quarter": 4,
    "cresRec": 0.107472025,
    "divBruta": 1162261000,
    "data": "12/31/2017 00:00:00",
    "qntAcoes": 357547200,
    "cotacao": 13.78,
    "pl": -76.82361,
    "pvp": 5.959727,
    "pebit": -61.6983337,
    "pfco": 133.6935,
    "psr": 29.1779041,
    "pAtivos": 2.41376066,
    "pCapGiro": 53.986042,
    "pAtivCLiq": -5.62823963,
    "divYeld": 0.00091065676,
    "evebit": -75.31258,
    "valordaFirma": 9505727000,
    "valordeMercado": 7787378000,
    "fci": 48277000,
    "dbPl": 0,
    "vpa": 3.65452981,
    "margBruta": 0.5615134,
    "capex": 84131000,
    "margLiq": -0.3798039,
    "capexLL": -0.8299644,
    "giroAtivos": 0.08272564,
    "fcf": 8097000,
    "caixaLivre": 0.47625953,
    "fcl": 1874000,
    "payout": 0,
    "lpa": -0.2835066,
    "margEbit": -0.472912371,
    "roic": 0,
    "ebitAtivo": -0.0391219743,
    "fco": 58248000,
    "dpa": 0.01254885,
    "liqCorrent": 1.36825955,
    "divBrPatrim": 0.88948524,
    "capexFco": 1.44435859,
    "fct": 0,
    "ativoCirculante": 535950000,
    "fciLL": 0.47625953,
    "capexDetails": 0,
    "roe": -0.0775767639,
    "roa": -0.03141952,
    "dlpl": 0.735485,
    "payoutDetails": 0,
    "ebit": -126217000,
    "lucroLiquido": -101367000,
    "receitaLiquida": 266893000
  },
  {
    "year": 2017,
    "quarter": 3,
    "cresRec": 0.105438814,
    "divBruta": 1160678000,
    "data": "09/30/2017 00:00:00",
    "qntAcoes": 357547200,
    "cotacao": 13.78,
    "pl": 284.040741,
    "pvp": 5.49543428,
    "pebit": 132.121719,
    "pfco": 276.392578,
    "psr": 30.5527611,
    "pAtivos": 2.41471171,
    "pCapGiro": 45.39786,
    "pAtivCLiq": -6.43218136,
    "divYeld": 0.00091065676,
    "evebit": 158.794266,
    "valordaFirma": 9363780000,
    "valordeMercado": 7790954000,
    "fci": 215840000,
    "dbPl": 0,
    "vpa": 3.96510983,
    "margBruta": 0.5471882,
    "capex": 46610000,
    "margLiq": 0.1075647,
    "capexLL": 1.69929636,
    "giroAtivos": 0.07903416,
    "fcf": -188548000,
    "caixaLivre": -7.869044,
    "fcl": 896000,
    "payout": 0,
    "lpa": 0.0767143443,
    "margEbit": 0.231247053,
    "roic": 0,
    "ebitAtivo": 0.0182764176,
    "fco": 28188000,
    "dpa": 0.01254885,
    "liqCorrent": 1.40296757,
    "divBrPatrim": 0.818696856,
    "capexFco": 1.65354049,
    "fct": 0,
    "ativoCirculante": 597493000,
    "fciLL": -7.869044,
    "capexDetails": 0,
    "roe": 0.0193473436,
    "roa": 0.008501286,
    "dlpl": 0.6522931,
    "payoutDetails": 0,
    "ebit": 58968000,
    "lucroLiquido": 27429000,
    "receitaLiquida": 255000000
  },
  {
    "year": 2017,
    "quarter": 2,
    "cresRec": 0.102422707,
    "divBruta": 977260000,
    "data": "06/30/2017 00:00:00",
    "qntAcoes": 357547200,
    "cotacao": 13.78,
    "pl": 364.794373,
    "pvp": 6.184746,
    "pebit": 186.738846,
    "pfco": 227.351486,
    "psr": 35.80538,
    "pAtivos": 2.85650349,
    "pCapGiro": 228.35141,
    "pAtivCLiq": -7.050768,
    "divYeld": 0.00091065676,
    "evebit": 220.4955,
    "valordaFirma": 10115450900,
    "valordeMercado": 8566831000,
    "fci": 71764000,
    "dbPl": 0,
    "vpa": 3.87404776,
    "margBruta": 0.5474398,
    "capex": 78595000,
    "margLiq": 0.09815223,
    "capexLL": 3.34674668,
    "giroAtivos": 0.07977861,
    "fcf": -35156000,
    "caixaLivre": -3.055868,
    "fcl": 1073000,
    "payout": 0,
    "lpa": 0.06568084,
    "margEbit": 0.1917404,
    "roic": 0,
    "ebitAtivo": 0.0152967824,
    "fco": 37681000,
    "dpa": 0.01254885,
    "liqCorrent": 1.103816,
    "divBrPatrim": 0.7055239,
    "capexFco": 2.08579922,
    "fct": 0,
    "ativoCirculante": 398886000,
    "fciLL": -3.055868,
    "capexDetails": 0,
    "roe": 0.0169540588,
    "roa": 0.007830448,
    "dlpl": 0.6583906,
    "payoutDetails": 0,
    "ebit": 45876000,
    "lucroLiquido": 23484000,
    "receitaLiquida": 239261000
  },
  {
    "year": 2017,
    "quarter": 1,
    "cresRec": 0.117895916,
    "divBruta": 941730000,
    "data": "03/31/2017 00:00:00",
    "qntAcoes": 357547200,
    "cotacao": 13.78,
    "pl": 389.8267,
    "pvp": 6.289683,
    "pebit": 151.08783,
    "pfco": 329.51886,
    "psr": 32.99402,
    "pAtivos": 2.913897,
    "pCapGiro": 81.9612045,
    "pAtivCLiq": -7.41439056,
    "divYeld": 0.000255157473,
    "evebit": 177.392365,
    "valordaFirma": 10058324000,
    "valordeMercado": 8566831000,
    "fci": 29097000,
    "dbPl": 0,
    "vpa": 3.809413,
    "margBruta": 0.580220163,
    "capex": 39096000,
    "margLiq": 0.0846376643,
    "capexLL": 1.77903163,
    "giroAtivos": 0.08831592,
    "fcf": -3662000,
    "caixaLivre": -1.32403529,
    "fcl": 563000,
    "payout": 0,
    "lpa": 0.06146321,
    "margEbit": 0.218376413,
    "roic": 0,
    "ebitAtivo": 0.0192861129,
    "fco": 25998000,
    "dpa": 0.00351607,
    "liqCorrent": 1.328699,
    "divBrPatrim": 0.6914089,
    "capexFco": 1.503808,
    "fct": 0,
    "ativoCirculante": 422513000,
    "fciLL": -1.32403529,
    "capexDetails": 0,
    "roe": 0.016134562,
    "roa": 0.00747485273,
    "dlpl": 0.627935946,
    "payoutDetails": 0,
    "ebit": 56701000,
    "lucroLiquido": 21976000,
    "receitaLiquida": 259648000
  },
  {
    "year": 2016,
    "quarter": 4,
    "cresRec": 0.114713795,
    "divBruta": 939076000,
    "data": "12/31/2016 00:00:00",
    "qntAcoes": 357547200,
    "cotacao": 13.78,
    "pl": 2046.05481,
    "pvp": 6.39764071,
    "pebit": 250.1849,
    "pfco": 374.342651,
    "psr": 34.9795074,
    "pAtivos": 2.955582,
    "pCapGiro": 57.19533,
    "pAtivCLiq": -7.43143463,
    "divYeld": 0.000255157473,
    "evebit": 292.9911,
    "valordaFirma": 10032601100,
    "valordeMercado": 8566831000,
    "fci": 126342000,
    "dbPl": 0,
    "vpa": 3.74513054,
    "margBruta": 0.555812359,
    "capex": 55928000,
    "margLiq": 0.0170960762,
    "capexLL": 13.3575354,
    "giroAtivos": 0.08449467,
    "fcf": -93746000,
    "caixaLivre": -30.1748276,
    "fcl": -9711000,
    "payout": 2.04561734,
    "lpa": 0.0117103411,
    "margEbit": 0.13981463,
    "roic": 0,
    "ebitAtivo": 0.0118135912,
    "fco": 22885000,
    "dpa": 0.00351607,
    "liqCorrent": 1.58303618,
    "divBrPatrim": 0.7012944,
    "capexFco": 2.4438715,
    "fct": 0,
    "ativoCirculante": 406682000,
    "fciLL": -30.1748276,
    "capexDetails": 0,
    "roe": 0.003126818,
    "roa": 0.0014445273,
    "dlpl": 0.631323755,
    "payoutDetails": 0,
    "ebit": 34242000,
    "lucroLiquido": 4187000,
    "receitaLiquida": 244910000
  },
  {
    "year": 2016,
    "quarter": 3,
    "cresRec": 0.1170023,
    "divBruta": 829664000,
    "data": "09/30/2016 00:00:00",
    "qntAcoes": 357547200,
    "cotacao": 13.78,
    "pl": -1274.06775,
    "pvp": 6.34326363,
    "pebit": 1066.58752,
    "pfco": -137.2142,
    "psr": 37.449482,
    "pAtivos": 3.069706,
    "pCapGiro": 92.4764252,
    "pAtivCLiq": -7.60301256,
    "divYeld": 0.000255157473,
    "evebit": 1241.72363,
    "valordaFirma": 9973524000,
    "valordeMercado": 8566831000,
    "fci": 3350000,
    "dbPl": 0,
    "vpa": 3.77723551,
    "margBruta": 0.5185896,
    "capex": 49525000,
    "margLiq": -0.0293936357,
    "capexLL": -7.36540747,
    "giroAtivos": 0.08196925,
    "fcf": -65248000,
    "caixaLivre": 0.498215348,
    "fcl": -536000,
    "payout": 0,
    "lpa": -0.018805908,
    "margEbit": 0.0351114944,
    "roic": 0,
    "ebitAtivo": 0.002878063,
    "fco": -62434000,
    "dpa": 0.00351607,
    "liqCorrent": 1.41951811,
    "divBrPatrim": 0.6143202,
    "capexFco": -0.7932377,
    "fct": 0,
    "ativoCirculante": 313458000,
    "fciLL": 0.498215348,
    "capexDetails": 0,
    "roe": -0.00497874944,
    "roa": -0.00240937434,
    "dlpl": 0.5894909,
    "payoutDetails": 0,
    "ebit": 8032000,
    "lucroLiquido": -6724000,
    "receitaLiquida": 228757000
  },
  {
    "year": 2016,
    "quarter": 2,
    "cresRec": 0.104287647,
    "divBruta": 809846000,
    "data": "06/30/2016 00:00:00",
    "qntAcoes": 357547200,
    "cotacao": 13.81,
    "pl": 215.755051,
    "pvp": 6.5386,
    "pebit": 110.223053,
    "pfco": 166.148026,
    "psr": 40.0588341,
    "pAtivos": 3.156076,
    "pCapGiro": 68.18679,
    "pAtivCLiq": -8.012328,
    "divYeld": 0.0002546032,
    "evebit": 127.235191,
    "valordaFirma": 9901443000,
    "valordeMercado": 8577557500,
    "fci": 52105000,
    "dbPl": 0,
    "vpa": 3.668981,
    "margBruta": 0.562613249,
    "capex": 45252000,
    "margLiq": 0.185668111,
    "capexLL": 1.13824332,
    "giroAtivos": 0.0787860155,
    "fcf": 5514000,
    "caixaLivre": -1.31061983,
    "fcl": -5993000,
    "payout": 0,
    "lpa": 0.111190908,
    "margEbit": 0.363434285,
    "roic": 0,
    "ebitAtivo": 0.0286335386,
    "fco": 51626000,
    "dpa": 0.00351607,
    "liqCorrent": 1.60011542,
    "divBrPatrim": 0.6173388,
    "capexFco": 0.876535058,
    "fct": 0,
    "ativoCirculante": 335413000,
    "fciLL": -1.31061983,
    "capexDetails": 0,
    "roe": 0.0303056631,
    "roa": 0.0146280508,
    "dlpl": 0.554775238,
    "payoutDetails": 0,
    "ebit": 77820000,
    "lucroLiquido": 39756000,
    "receitaLiquida": 214124000
  },
  {
    "year": 2016,
    "quarter": 1,
    "cresRec": 0.112238675,
    "divBruta": 812470000,
    "data": "03/31/2016 00:00:00",
    "qntAcoes": 357547200,
    "cotacao": 9.92,
    "pl": -564.718445,
    "pvp": 3.917694,
    "pebit": 120.741005,
    "pfco": -114.122978,
    "psr": 21.75134,
    "pAtivos": 1.86175859,
    "pCapGiro": 31.8645954,
    "pAtivCLiq": -4.62134933,
    "divYeld": 0.0024836713,
    "evebit": 152.833435,
    "valordaFirma": 6322566660,
    "valordeMercado": 4994935000,
    "fci": 103648000,
    "dbPl": 0,
    "vpa": 3.56587315,
    "margBruta": 0.565076351,
    "capex": 89455000,
    "margLiq": -0.0385171436,
    "capexLL": -10.1136236,
    "giroAtivos": 0.08559282,
    "fcf": -59087000,
    "caixaLivre": 11.7182589,
    "fcl": -88329000,
    "payout": 0,
    "lpa": -0.0247379914,
    "margEbit": 0.180148751,
    "roic": 0,
    "ebitAtivo": 0.0154194394,
    "fco": -43768000,
    "dpa": 0.02463802,
    "liqCorrent": 1.92019367,
    "divBrPatrim": 0.6372474,
    "capexFco": -2.0438447,
    "fct": 0,
    "ativoCirculante": 327105000,
    "fciLL": 11.7182589,
    "capexDetails": 0,
    "roe": -0.006937429,
    "roa": -0.00329679088,
    "dlpl": 0.574256,
    "payoutDetails": 0,
    "ebit": 41369000,
    "lucroLiquido": -8845000,
    "receitaLiquida": 229638000
  },
  {
    "year": 2015,
    "quarter": 4,
    "cresRec": 0.1120204,
    "divBruta": 758373000,
    "data": "12/31/2015 00:00:00",
    "qntAcoes": 357547200,
    "cotacao": 9.92,
    "pl": -8366.725,
    "pvp": 3.90588427,
    "pebit": 268.3429,
    "pfco": -199.709518,
    "psr": 23.54513,
    "pAtivos": 1.87199533,
    "pCapGiro": 30.3030014,
    "pAtivCLiq": -5.02364969,
    "divYeld": 0.0024836713,
    "evebit": 334.563,
    "valordaFirma": 6227556000,
    "valordeMercado": 4994935000,
    "fci": 101037000,
    "dbPl": 0,
    "vpa": 3.576655,
    "margBruta": 0.484182835,
    "capex": 91534000,
    "margLiq": -0.00281413947,
    "capexLL": -153.323288,
    "giroAtivos": 0.07950669,
    "fcf": -213943000,
    "caixaLivre": 169.241211,
    "fcl": 87895000,
    "payout": -21.5728645,
    "lpa": -0.00166970957,
    "margEbit": 0.0877427,
    "roic": 0,
    "ebitAtivo": 0.00697613135,
    "fco": -25011000,
    "dpa": 0.02463802,
    "liqCorrent": 1.71572852,
    "divBrPatrim": 0.5930242,
    "capexFco": -3.65974975,
    "fct": 0,
    "ativoCirculante": 395134000,
    "fciLL": 169.241211,
    "capexDetails": 0,
    "roe": -0.0004668355,
    "roa": -0.000223742914,
    "dlpl": 0.4704138,
    "payoutDetails": 0,
    "ebit": 18614000,
    "lucroLiquido": -597000,
    "receitaLiquida": 212143000
  },
  {
    "year": 2015,
    "quarter": 3,
    "cresRec": 0.107097872,
    "divBruta": 531131000,
    "data": "09/30/2015 00:00:00",
    "qntAcoes": 357547200,
    "cotacao": 9.92,
    "pl": -9813.231,
    "pvp": 3.86389828,
    "pebit": 185.395828,
    "pfco": 127.172,
    "psr": 24.5977135,
    "pAtivos": 1.99707913,
    "pCapGiro": 238.94635,
    "pAtivCLiq": -5.457567,
    "divYeld": 0.0024836713,
    "evebit": 228.037766,
    "valordaFirma": 6143793660,
    "valordeMercado": 4994935000,
    "fci": 64597000,
    "dbPl": 0,
    "vpa": 3.61551976,
    "margBruta": 0.517509162,
    "capex": 100235000,
    "margLiq": -0.00250658649,
    "capexLL": -196.925339,
    "giroAtivos": 0.081189625,
    "fcf": -26348000,
    "caixaLivre": 126.90963,
    "fcl": 1028000,
    "payout": 20.5874271,
    "lpa": -0.00142358826,
    "margEbit": 0.132676736,
    "roic": 0,
    "ebitAtivo": 0.010771974,
    "fco": 39277000,
    "dpa": 0.02463802,
    "liqCorrent": 1.07677782,
    "divBrPatrim": 0.410863459,
    "capexFco": 2.55200243,
    "fct": 0,
    "ativoCirculante": 293170000,
    "fciLL": 126.90963,
    "capexDetails": 0,
    "roe": -0.000393743743,
    "roa": -0.000203508826,
    "dlpl": 0.36480394,
    "payoutDetails": 0,
    "ebit": 26942000,
    "lucroLiquido": -509000,
    "receitaLiquida": 203065000
  },
  {
    "year": 2015,
    "quarter": 2,
    "cresRec": 0.09099364,
    "divBruta": 502201000,
    "data": "06/30/2015 00:00:00",
    "qntAcoes": 357547200,
    "cotacao": 9.92,
    "pl": 2959.08447,
    "pvp": 3.85467839,
    "pebit": 215.475372,
    "pfco": 175.4209,
    "psr": 26.7978649,
    "pAtivos": 2.0588057,
    "pCapGiro": 55.3627129,
    "pAtivCLiq": -6.02607441,
    "divYeld": 0.0024836713,
    "evebit": 260.846619,
    "valordaFirma": 6046685700,
    "valordeMercado": 4994935000,
    "fci": 39608000,
    "dbPl": 0,
    "vpa": 3.62416744,
    "margBruta": 0.491853237,
    "capex": 60305000,
    "margLiq": 0.009056134,
    "capexLL": 35.72571,
    "giroAtivos": 0.07682723,
    "fcf": -12258000,
    "caixaLivre": -23.4644547,
    "fcl": 1124000,
    "payout": 0,
    "lpa": 0.004721055,
    "margEbit": 0.124366261,
    "roic": 0,
    "ebitAtivo": 0.009554715,
    "fco": 28474000,
    "dpa": 0.02463802,
    "liqCorrent": 1.42716324,
    "divBrPatrim": 0.3875573,
    "capexFco": 2.117897,
    "fct": 0,
    "ativoCirculante": 301434000,
    "fciLL": -23.4644547,
    "capexDetails": 0,
    "roe": 0.00130265916,
    "roa": 0.0006957577,
    "dlpl": 0.32692346,
    "payoutDetails": 0,
    "ebit": 23181000,
    "lucroLiquido": 1688000,
    "receitaLiquida": 186393000
  },
  {
    "year": 2015,
    "quarter": 1,
    "cresRec": 0.0994400457,
    "divBruta": 497786000,
    "data": "03/31/2015 00:00:00",
    "qntAcoes": 357547200,
    "cotacao": 9.95,
    "pl": 483.4519,
    "pvp": 3.89157963,
    "pebit": 132.656525,
    "pfco": 992.005737,
    "psr": 25.6274757,
    "pAtivos": 2.06197929,
    "pCapGiro": 39.378994,
    "pAtivCLiq": -6.28298569,
    "divYeld": 0.001565804,
    "evebit": 160.297638,
    "valordaFirma": 6048671000,
    "valordeMercado": 5005661000,
    "fci": 18453000,
    "dbPl": 0,
    "vpa": 3.59751081,
    "margBruta": 0.5648666,
    "capex": 52255000,
    "margLiq": 0.0530093573,
    "capexLL": 5.04684162,
    "giroAtivos": 0.0804597139,
    "fcf": -5700000,
    "caixaLivre": -1.78220975,
    "fcl": -7707000,
    "payout": 0,
    "lpa": 0.0289584137,
    "margEbit": 0.1931867,
    "roic": 0,
    "ebitAtivo": 0.0155437468,
    "fco": 5046000,
    "dpa": 0.01557975,
    "liqCorrent": 1.584426,
    "divBrPatrim": 0.3869966,
    "capexFco": 10.3557272,
    "fct": 0,
    "ativoCirculante": 344619000,
    "fciLL": -1.78220975,
    "capexDetails": 0,
    "roe": 0.008049569,
    "roa": 0.004265118,
    "dlpl": 0.3105669,
    "payoutDetails": 0,
    "ebit": 37734000,
    "lucroLiquido": 10354000,
    "receitaLiquida": 195324000
  },
  {
    "year": 2014,
    "quarter": 4,
    "cresRec": 0.120221652,
    "divBruta": 489636000,
    "data": "12/31/2014 00:00:00",
    "qntAcoes": 357547200,
    "cotacao": 9.95,
    "pl": 355.439972,
    "pvp": 3.91564059,
    "pebit": 138.83403,
    "pfco": 82.70676,
    "psr": 25.478899,
    "pAtivos": 2.0786283,
    "pCapGiro": 32.13433,
    "pAtivCLiq": -6.525052,
    "divYeld": 0.001565804,
    "evebit": 166.55452,
    "valordaFirma": 6005123000,
    "valordeMercado": 5005661000,
    "fci": 46422000,
    "dbPl": 0,
    "vpa": 3.57540464,
    "margBruta": 0.389121622,
    "capex": 71722000,
    "margLiq": 0.07168271,
    "capexLL": 5.092807,
    "giroAtivos": 0.08158234,
    "fcf": 12876000,
    "caixaLivre": -3.29631472,
    "fcl": 1225000,
    "payout": 1.94930053,
    "lpa": 0.0393878035,
    "margEbit": 0.183520555,
    "roic": 0,
    "ebitAtivo": 0.0149720367,
    "fco": 60523000,
    "dpa": 0.01557975,
    "liqCorrent": 1.75302863,
    "divBrPatrim": 0.383014083,
    "capexFco": 1.18503714,
    "fct": 0,
    "ativoCirculante": 362635000,
    "fciLL": -3.29631472,
    "capexDetails": 0,
    "roe": 0.01101632,
    "roa": 0.005848043,
    "dlpl": 0.2810738,
    "payoutDetails": 0,
    "ebit": 36055000,
    "lucroLiquido": 14083000,
    "receitaLiquida": 196463000
  },
  {
    "year": 2014,
    "quarter": 3,
    "cresRec": 0.108743489,
    "divBruta": 475075000,
    "data": "09/30/2014 00:00:00",
    "qntAcoes": 357547200,
    "cotacao": 9.95,
    "pl": -625.0045,
    "pvp": 3.87516046,
    "pebit": 526.8008,
    "pfco": -733.4302,
    "psr": 27.1288948,
    "pAtivos": 2.088875,
    "pCapGiro": 22.5442657,
    "pAtivCLiq": -7.201447,
    "divYeld": 0.001565804,
    "evebit": 625.574646,
    "valordaFirma": 5944210000,
    "valordeMercado": 5005661000,
    "fci": 37386000,
    "dbPl": 0,
    "vpa": 3.61275363,
    "margBruta": 0.571913242,
    "capex": 48930000,
    "margLiq": -0.04340592,
    "capexLL": -6.109377,
    "giroAtivos": 0.07699816,
    "fcf": -44645000,
    "caixaLivre": 4.66799831,
    "fcl": 434000,
    "payout": 1.32775629,
    "lpa": -0.022399839,
    "margEbit": 0.05149745,
    "roic": 0,
    "ebitAtivo": 0.003965209,
    "fco": -6825000,
    "dpa": 0.01557975,
    "liqCorrent": 2.184292,
    "divBrPatrim": 0.367781967,
    "capexFco": -7.169231,
    "fct": 0,
    "ativoCirculante": 409522000,
    "fciLL": 4.66799831,
    "capexDetails": 0,
    "roe": -0.006200212,
    "roa": -0.003342176,
    "dlpl": 0.239222586,
    "payoutDetails": 0,
    "ebit": 9502000,
    "lucroLiquido": -8009000,
    "receitaLiquida": 184514000
  },
  {
    "year": 2014,
    "quarter": 2,
    "cresRec": 0.09820794,
    "divBruta": 428025000,
    "data": "06/30/2014 00:00:00",
    "qntAcoes": 357547200,
    "cotacao": 9.95,
    "pl": 72.640564,
    "pvp": 3.84416866,
    "pebit": 41.52077,
    "pfco": -333.37735,
    "psr": 28.5367565,
    "pAtivos": 2.09838986,
    "pCapGiro": 19.4737186,
    "pAtivCLiq": -7.70620966,
    "divYeld": 0.001565804,
    "evebit": 49.0246849,
    "valordaFirma": 5910318000,
    "valordeMercado": 5005661000,
    "fci": 68131000,
    "dbPl": 0,
    "vpa": 3.6418798,
    "margBruta": 0.602237046,
    "capex": 34041000,
    "margLiq": 0.3928488,
    "capexLL": 0.49399215,
    "giroAtivos": 0.07353288,
    "fcf": -86287000,
    "caixaLivre": -0.9886954,
    "fcl": 3141000,
    "payout": 0,
    "lpa": 0.192729786,
    "margEbit": 0.6872887,
    "roic": 0,
    "ebitAtivo": 0.05053832,
    "fco": -15015000,
    "dpa": 0.01557975,
    "liqCorrent": 2.454511,
    "divBrPatrim": 0.328707874,
    "capexFco": -2.26713276,
    "fct": 0,
    "ativoCirculante": 433771000,
    "fciLL": -0.9886954,
    "capexDetails": 0,
    "roe": 0.052920416,
    "roa": 0.0288873035,
    "dlpl": 0.191491112,
    "payoutDetails": 0,
    "ebit": 120558000,
    "lucroLiquido": 68910000,
    "receitaLiquida": 175411000
  },
  {
    "year": 2014,
    "quarter": 1,
    "cresRec": 0.115559474,
    "divBruta": 349035000,
    "data": "03/31/2014 00:00:00",
    "qntAcoes": 357547200,
    "cotacao": 9.95,
    "pl": -20022.6445,
    "pvp": 4.0831275,
    "pebit": 152.807281,
    "pfco": 200.458969,
    "psr": 26.5823059,
    "pAtivos": 2.14940763,
    "pCapGiro": 67.77137,
    "pAtivCLiq": -6.569445,
    "divYeld": 0,
    "evebit": 182.619171,
    "valordaFirma": 5982239000,
    "valordeMercado": 5005661000,
    "fci": 48236000,
    "dbPl": 0,
    "vpa": 3.42874432,
    "margBruta": 0.649213,
    "capex": 26872000,
    "margLiq": -0.0013276122,
    "capexLL": -107.488,
    "giroAtivos": 0.08085859,
    "fcf": -24803000,
    "caixaLivre": 192.944,
    "fcl": 1538000,
    "payout": 0,
    "lpa": -0.000699208351,
    "margEbit": 0.173959687,
    "roic": 0,
    "ebitAtivo": 0.0140661336,
    "fco": 24971000,
    "dpa": 0,
    "liqCorrent": 1.27653348,
    "divBrPatrim": 0.28470853,
    "capexFco": 1.07612836,
    "fct": 0,
    "ativoCirculante": 340957000,
    "fciLL": 192.944,
    "capexDetails": 0,
    "roe": -0.00020392549,
    "roa": -0.000107348846,
    "dlpl": 0.18165274,
    "payoutDetails": 0,
    "ebit": 32758000,
    "lucroLiquido": -250000,
    "receitaLiquida": 188308000
  },
  {
    "year": 2013,
    "quarter": 4,
    "cresRec": 0.119489416,
    "divBruta": 330143000,
    "data": "12/31/2013 00:00:00",
    "qntAcoes": 357547200,
    "cotacao": 9.95,
    "pl": 230.5269,
    "pvp": 4.10207272,
    "pebit": 113.574013,
    "pfco": 60.3215256,
    "psr": 28.5980568,
    "pAtivos": 2.1493597,
    "pCapGiro": 57.55221,
    "pAtivCLiq": -6.56246042,
    "divYeld": 0.0008508472,
    "evebit": 135.989929,
    "valordaFirma": 5993620000,
    "valordeMercado": 5005661000,
    "fci": 97487000,
    "dbPl": 0,
    "vpa": 3.41290879,
    "margBruta": 0.416796654,
    "capex": 40907000,
    "margLiq": 0.124055192,
    "capexLL": 1.88389981,
    "giroAtivos": 0.07515754,
    "fcf": -14018000,
    "caixaLivre": -4.489592,
    "fcl": -486000,
    "payout": 0.714654148,
    "lpa": 0.0607304424,
    "margEbit": 0.251801074,
    "roic": 0,
    "ebitAtivo": 0.0189247485,
    "fco": 82983000,
    "dpa": 0.00846593,
    "liqCorrent": 1.33596516,
    "divBrPatrim": 0.2705478,
    "capexFco": 0.4929564,
    "fct": 0,
    "ativoCirculante": 345860000,
    "fciLL": -4.489592,
    "capexDetails": 0,
    "roe": 0.0177943353,
    "roa": 0.009323683,
    "dlpl": 0.17165789,
    "payoutDetails": 0,
    "ebit": 44074000,
    "lucroLiquido": 21714000,
    "receitaLiquida": 175035000
  },
  {
    "year": 2013,
    "quarter": 3,
    "cresRec": 0.10657794,
    "divBruta": 259236000,
    "data": "09/30/2013 00:00:00",
    "qntAcoes": 357547200,
    "cotacao": 9.95,
    "pl": 685.0501,
    "pvp": 3.987145,
    "pebit": 226.551758,
    "pfco": 207.008026,
    "psr": 30.2559242,
    "pAtivos": 2.191368,
    "pCapGiro": 105.722878,
    "pAtivCLiq": -6.667263,
    "divYeld": 0.0008508472,
    "evebit": 270.192139,
    "valordaFirma": 5969895000,
    "valordeMercado": 5005661000,
    "fci": 41377000,
    "dbPl": 0,
    "vpa": 3.51128459,
    "margBruta": 0.618596,
    "capex": 32524000,
    "margLiq": 0.0441660024,
    "capexLL": 4.451074,
    "giroAtivos": 0.0724277347,
    "fcf": -17529000,
    "caixaLivre": -5.662652,
    "fcl": 333000,
    "payout": 0,
    "lpa": 0.020436462,
    "margEbit": 0.13354972,
    "roic": 0,
    "ebitAtivo": 0.009672704,
    "fco": 24181000,
    "dpa": 0.00846593,
    "liqCorrent": 1.20524609,
    "divBrPatrim": 0.2064885,
    "capexFco": 1.34502292,
    "fct": 0,
    "ativoCirculante": 278031000,
    "fciLL": -5.662652,
    "capexDetails": 0,
    "roe": 0.0058202236,
    "roa": 0.00319884345,
    "dlpl": 0.155049577,
    "payoutDetails": 0,
    "ebit": 22095000,
    "lucroLiquido": 7307000,
    "receitaLiquida": 165444000
  },
  {
    "year": 2013,
    "quarter": 2,
    "cresRec": 0.09110831,
    "divBruta": 240618000,
    "data": "06/30/2013 00:00:00",
    "qntAcoes": 357547200,
    "cotacao": 9.95,
    "pl": 859.340942,
    "pvp": 4.00168943,
    "pebit": 264.458,
    "pfco": 496.347137,
    "psr": 31.95504,
    "pAtivos": 2.22313666,
    "pCapGiro": 271.589233,
    "pAtivCLiq": -6.74078655,
    "divYeld": 0.0008508472,
    "evebit": 314.4021,
    "valordaFirma": 5951003000,
    "valordeMercado": 5005661000,
    "fci": 2816000,
    "dbPl": 0,
    "vpa": 3.49852252,
    "margBruta": 0.609599948,
    "capex": 20318000,
    "margLiq": 0.03718552,
    "capexLL": 3.48806858,
    "giroAtivos": 0.0695707649,
    "fcf": 6686000,
    "caixaLivre": -0.483433485,
    "fcl": 583000,
    "payout": 0,
    "lpa": 0.016291555,
    "margEbit": 0.12083219,
    "roic": 0,
    "ebitAtivo": 0.008406389,
    "fco": 10085000,
    "dpa": 0.00846593,
    "liqCorrent": 1.0768888,
    "divBrPatrim": 0.1923579,
    "capexFco": 2.01467538,
    "fct": 0,
    "ativoCirculante": 258141000,
    "fciLL": -0.483433485,
    "capexDetails": 0,
    "roe": 0.00465669576,
    "roa": 0.002587025,
    "dlpl": 0.14807573,
    "payoutDetails": 0,
    "ebit": 18928000,
    "lucroLiquido": 5825000,
    "receitaLiquida": 156647000
  },
  {
    "year": 2013,
    "quarter": 1,
    "cresRec": 0.1022378,
    "divBruta": 249569000,
    "data": "03/31/2013 00:00:00",
    "qntAcoes": 357547200,
    "cotacao": 9.95,
    "pl": 737.5937,
    "pvp": 3.9989686,
    "pebit": 272.891846,
    "pfco": 124.32225,
    "psr": 30.5228062,
    "pAtivos": 2.20231771,
    "pCapGiro": 176.915359,
    "pAtivCLiq": -6.630228,
    "divYeld": 0.0008508472,
    "evebit": 324.998657,
    "valordaFirma": 5918875000,
    "valordeMercado": 4969906000,
    "fci": 45168000,
    "dbPl": 0,
    "vpa": 3.47589612,
    "margBruta": 0.625803,
    "capex": 20906000,
    "margLiq": 0.0413815975,
    "capexLL": 3.10270119,
    "giroAtivos": 0.07215319,
    "fcf": -11126000,
    "caixaLivre": -6.70347261,
    "fcl": 5934000,
    "payout": 0,
    "lpa": 0.0188450627,
    "margEbit": 0.111849457,
    "roic": 0,
    "ebitAtivo": 0.008070295,
    "fco": 39976000,
    "dpa": 0.00846593,
    "liqCorrent": 1.11893356,
    "divBrPatrim": 0.200812355,
    "capexFco": 0.522963762,
    "fct": 0,
    "ativoCirculante": 264291000,
    "fciLL": -6.70347261,
    "capexDetails": 0,
    "roe": 0.00542164175,
    "roa": 0.00298581412,
    "dlpl": 0.148587421,
    "payoutDetails": 0,
    "ebit": 18212000,
    "lucroLiquido": 6738000,
    "receitaLiquida": 162826000
  },
  {
    "year": 2012,
    "quarter": 4,
    "cresRec": 0.133193865,
    "divBruta": 237861000,
    "data": "12/31/2012 00:00:00",
    "qntAcoes": 357547200,
    "cotacao": 9.95,
    "pl": 656.027161,
    "pvp": 4.585566,
    "pebit": 264.862152,
    "pfco": 85.38923,
    "psr": 35.3967361,
    "pAtivos": 2.52336216,
    "pCapGiro": 351.1921,
    "pAtivCLiq": -7.52221727,
    "divYeld": 0.0003579417,
    "evebit": 310.444977,
    "valordaFirma": 6646627000,
    "valordeMercado": 5670699000,
    "fci": 6086000,
    "dbPl": 0,
    "vpa": 3.458679,
    "margBruta": 0.6206462,
    "capex": 23163000,
    "margLiq": 0.0539562069,
    "capexLL": 2.67966223,
    "giroAtivos": 0.07128799,
    "fcf": 59502000,
    "caixaLivre": -0.7040722,
    "fcl": 822000,
    "payout": 0.849491,
    "lpa": 0.0241758283,
    "margEbit": 0.1336421,
    "roic": 0,
    "ebitAtivo": 0.009527077,
    "fco": 66410000,
    "dpa": 0.00356152,
    "liqCorrent": 1.06710279,
    "divBrPatrim": 0.192344427,
    "capexFco": 0.348787844,
    "fct": 0,
    "ativoCirculante": 256778000,
    "fciLL": -0.7040722,
    "capexDetails": 0,
    "roe": 0.00698990235,
    "roa": 0.00384642929,
    "dlpl": 0.164276451,
    "payoutDetails": 0,
    "ebit": 21410000,
    "lucroLiquido": 8644000,
    "receitaLiquida": 160204000
  },
  {
    "year": 2012,
    "quarter": 3,
    "cresRec": 0.124814279,
    "divBruta": 245824000,
    "data": "09/30/2012 00:00:00",
    "qntAcoes": 357547200,
    "cotacao": 9.95,
    "pl": 1025.06567,
    "pvp": 6.893474,
    "pebit": 452.343079,
    "pfco": 398.549164,
    "psr": 57.0999756,
    "pAtivos": 3.83788586,
    "pCapGiro": 291.805267,
    "pAtivCLiq": -11.7432737,
    "divYeld": 0.0003579417,
    "evebit": 501.973022,
    "valordaFirma": 9788473000,
    "valordeMercado": 8820690000,
    "fci": 17095000,
    "dbPl": 0,
    "vpa": 3.578747,
    "margBruta": 0.637385249,
    "capex": 29213000,
    "margLiq": 0.0557037257,
    "capexLL": 3.39488673,
    "giroAtivos": 0.0672134459,
    "fcf": 4337000,
    "caixaLivre": -1.98663568,
    "fcl": 700000,
    "payout": 0,
    "lpa": 0.0240667518,
    "margEbit": 0.126231566,
    "roic": 0,
    "ebitAtivo": 0.008484459,
    "fco": 22132000,
    "dpa": 0.00356152,
    "liqCorrent": 1.12733257,
    "divBrPatrim": 0.192114383,
    "capexFco": 1.319944,
    "fct": 0,
    "ativoCirculante": 267622000,
    "fciLL": -1.98663568,
    "capexDetails": 0,
    "roe": 0.00672491034,
    "roa": 0.00374403922,
    "dlpl": 0.152284637,
    "payoutDetails": 0,
    "ebit": 19500000,
    "lucroLiquido": 8605000,
    "receitaLiquida": 154478000
  },
  {
    "year": 2012,
    "quarter": 2,
    "cresRec": 0.10384053,
    "divBruta": 249290000,
    "data": "06/30/2012 00:00:00",
    "qntAcoes": 357547200,
    "cotacao": 9.95,
    "pl": -3419.71582,
    "pvp": 5.555062,
    "pebit": 3871.30566,
    "pfco": 498.703522,
    "psr": 48.082737,
    "pAtivos": 3.08223915,
    "pCapGiro": 165.3862,
    "pAtivCLiq": -9.463254,
    "divYeld": 0.0003579417,
    "evebit": 4396.23047,
    "valordaFirma": 8023121000,
    "valordeMercado": 7065133000,
    "fci": 4931000,
    "dbPl": 0,
    "vpa": 3.55711627,
    "margBruta": 0.6040752,
    "capex": 28876000,
    "margLiq": -0.0140604479,
    "capexLL": -13.9767666,
    "giroAtivos": 0.06410282,
    "fcf": 9060000,
    "caixaLivre": 2.38673759,
    "fcl": 176000,
    "payout": 0,
    "lpa": -0.00577825774,
    "margEbit": 0.0124202892,
    "roic": 0,
    "ebitAtivo": 0.000796175562,
    "fco": 14167000,
    "dpa": 0.00356152,
    "liqCorrent": 1.18487787,
    "divBrPatrim": 0.196007818,
    "capexFco": 2.03825784,
    "fct": 0,
    "ativoCirculante": 273785000,
    "fciLL": 2.38673759,
    "capexDetails": 0,
    "roe": -0.001624422,
    "roa": -0.0009013144,
    "dlpl": 0.146958292,
    "payoutDetails": 0,
    "ebit": 1825000,
    "lucroLiquido": -2066000,
    "receitaLiquida": 146937000
  },
  {
    "year": 2012,
    "quarter": 1,
    "cresRec": 0.105961829,
    "divBruta": 253614000,
    "data": "03/31/2012 00:00:00",
    "qntAcoes": 357547200,
    "cotacao": 4.43,
    "pl": 475.965027,
    "pvp": 2.325246,
    "pebit": 337.923248,
    "pfco": 94.10033,
    "psr": 19.954155,
    "pAtivos": 1.28718257,
    "pCapGiro": 53.3729324,
    "pAtivCLiq": -3.99158263,
    "divYeld": 0.000803954841,
    "evebit": 446.4326,
    "valordaFirma": 3920571000,
    "valordeMercado": 2967641860,
    "fci": 25844000,
    "dbPl": 0,
    "vpa": 3.56951451,
    "margBruta": 0.6305884,
    "capex": 23417000,
    "margLiq": 0.0419235751,
    "capexLL": 3.75573373,
    "giroAtivos": 0.06450699,
    "fcf": 4130000,
    "caixaLivre": -4.144988,
    "fcl": 1563000,
    "payout": 0,
    "lpa": 0.0174382571,
    "margEbit": 0.0590493754,
    "roic": 0,
    "ebitAtivo": 0.00380909746,
    "fco": 31537000,
    "dpa": 0.00356152,
    "liqCorrent": 1.24155247,
    "divBrPatrim": 0.198715,
    "capexFco": 0.7425246,
    "fct": 0,
    "ativoCirculante": 285788000,
    "fciLL": -4.144988,
    "capexDetails": 0,
    "roe": 0.00488533,
    "roa": 0.00270436378,
    "dlpl": 0.13890478,
    "payoutDetails": 0,
    "ebit": 8782000,
    "lucroLiquido": 6235000,
    "receitaLiquida": 148723000
  },
  {
    "year": 2011,
    "quarter": 4,
    "cresRec": 0.140577286,
    "divBruta": 258622000,
    "data": "12/31/2011 00:00:00",
    "qntAcoes": 357547200,
    "cotacao": 4.43,
    "pl": 414.185883,
    "pvp": 2.32228374,
    "pebit": 242.990417,
    "pfco": 12.681797,
    "psr": 20.85556,
    "pAtivos": 1.29675663,
    "pCapGiro": 57.85441,
    "pAtivCLiq": -4.01220846,
    "divYeld": 0,
    "evebit": 319.815765,
    "valordaFirma": 3905910000,
    "valordeMercado": 2967641860,
    "fci": -4578000,
    "dbPl": 0,
    "vpa": 3.57406783,
    "margBruta": 0.6585755,
    "capex": 19155000,
    "margLiq": 0.05035314,
    "capexLL": 2.67341232,
    "giroAtivos": 0.0621779822,
    "fcf": 239120000,
    "caixaLivre": 0.638939261,
    "fcl": -534000,
    "payout": 0.6415911,
    "lpa": 0.02003931,
    "margEbit": 0.08582874,
    "roic": 0,
    "ebitAtivo": 0.00533665763,
    "fco": 234008000,
    "dpa": 0,
    "liqCorrent": 1.23351467,
    "divBrPatrim": 0.202380791,
    "capexFco": 0.0818561763,
    "fct": 0,
    "ativoCirculante": 270960000,
    "fciLL": 0.638939261,
    "capexDetails": 0,
    "roe": 0.00560686365,
    "roa": 0.00313085667,
    "dlpl": 0.145768285,
    "payoutDetails": 0,
    "ebit": 12213000,
    "lucroLiquido": 7165000,
    "receitaLiquida": 142295000
  },
  {
    "year": 2011,
    "quarter": 3,
    "cresRec": 0.07745481,
    "divBruta": 259643000,
    "data": "09/30/2011 00:00:00",
    "qntAcoes": 357547200,
    "cotacao": 4.43,
    "pl": 259.024353,
    "pvp": 2.948058,
    "pebit": 149.6768,
    "pfco": 171.649139,
    "psr": 22.5583553,
    "pAtivos": 1.59940517,
    "pCapGiro": 28.8588486,
    "pAtivCLiq": -5.212397,
    "divYeld": 0,
    "evebit": 187.615524,
    "valordaFirma": 3719852800,
    "valordeMercado": 2967641860,
    "fci": 62618000,
    "dbPl": 0,
    "vpa": 2.81541276,
    "margBruta": 0.627689,
    "capex": 26196000,
    "margLiq": 0.08708971,
    "capexLL": 2.28646231,
    "giroAtivos": 0.07090079,
    "fcf": -44638000,
    "caixaLivre": -5.46548,
    "fcl": -691000,
    "payout": 0,
    "lpa": 0.03204332,
    "margEbit": 0.150713772,
    "roic": 0,
    "ebitAtivo": 0.0106857251,
    "fco": 17289000,
    "dpa": 0,
    "liqCorrent": 1.58213842,
    "divBrPatrim": 0.257929564,
    "capexFco": 1.51518309,
    "fct": 0,
    "ativoCirculante": 279480000,
    "fciLL": -5.46548,
    "capexDetails": 0,
    "roe": 0.0113813933,
    "roa": 0.006174729,
    "dlpl": 0.161955133,
    "payoutDetails": 0,
    "ebit": 19827000,
    "lucroLiquido": 11457000,
    "receitaLiquida": 131554000
  },
  {
    "year": 2011,
    "quarter": 2,
    "cresRec": 0.08127405,
    "divBruta": 217173000,
    "data": "06/30/2011 00:00:00",
    "qntAcoes": 357547200,
    "cotacao": 3.93,
    "pl": -123.6639,
    "pvp": 2.80847144,
    "pebit": -142.4491,
    "pfco": 90.64479,
    "psr": 21.3881741,
    "pAtivos": 1.55503249,
    "pCapGiro": 25.3002167,
    "pAtivCLiq": -4.93987942,
    "divYeld": 0,
    "evebit": -180.223373,
    "valordaFirma": 3528413180,
    "valordeMercado": 2788868350,
    "fci": 35592000,
    "dbPl": 0,
    "vpa": 2.77731156,
    "margBruta": 0.648156,
    "capex": 16651000,
    "margLiq": -0.172954068,
    "capexLL": -0.738338053,
    "giroAtivos": 0.07270525,
    "fcf": -3862000,
    "caixaLivre": 1.57821918,
    "fcl": -963000,
    "payout": 0,
    "lpa": -0.06307419,
    "margEbit": -0.1501461,
    "roic": 0,
    "ebitAtivo": -0.0109164082,
    "fco": 30767000,
    "dpa": 0,
    "liqCorrent": 1.87739789,
    "divBrPatrim": 0.21869953,
    "capexFco": 0.541196764,
    "fct": 0,
    "ativoCirculante": 235865000,
    "fciLL": 1.57821918,
    "capexDetails": 0,
    "roe": -0.0227105189,
    "roa": -0.012574668,
    "dlpl": 0.157389581,
    "payoutDetails": 0,
    "ebit": -19578000,
    "lucroLiquido": -22552000,
    "receitaLiquida": 130393000
  },
  {
    "year": 2011,
    "quarter": 1,
    "cresRec": 0.109573156,
    "divBruta": 213309000,
    "data": "03/31/2011 00:00:00",
    "qntAcoes": 357547200,
    "cotacao": 3.93,
    "pl": 235.665726,
    "pvp": 2.746106,
    "pebit": 110.175339,
    "pfco": 141.459213,
    "psr": 20.6716061,
    "pAtivos": 1.59257245,
    "pCapGiro": 32.1290779,
    "pAtivCLiq": -5.24937773,
    "divYeld": 0.003173486,
    "evebit": 137.5406,
    "valordaFirma": 3481565180,
    "valordeMercado": 2788868350,
    "fci": 24537000,
    "dbPl": 0,
    "vpa": 2.84038568,
    "margBruta": 0.7037572,
    "capex": 11371000,
    "margLiq": 0.08771579,
    "capexLL": 0.960875452,
    "giroAtivos": 0.077041544,
    "fcf": -4608000,
    "caixaLivre": -2.07343245,
    "fcl": -214000,
    "payout": 0,
    "lpa": 0.0330977254,
    "margEbit": 0.187624618,
    "roic": 0,
    "ebitAtivo": 0.014454891,
    "fco": 19715000,
    "dpa": 0.0124718,
    "liqCorrent": 1.73860216,
    "divBrPatrim": 0.210038289,
    "capexFco": 0.576768935,
    "fct": 0,
    "ativoCirculante": 204324000,
    "fciLL": -2.07343245,
    "capexDetails": 0,
    "roe": 0.0116525469,
    "roa": 0.00675776,
    "dlpl": 0.167793125,
    "payoutDetails": 0,
    "ebit": 25313000,
    "lucroLiquido": 11834000,
    "receitaLiquida": 134913000
  },
  {
    "year": 2010,
    "quarter": 4,
    "cresRec": 0,
    "divBruta": 208701000,
    "data": "12/31/2010 00:00:00",
    "qntAcoes": 357547200,
    "cotacao": 4.26,
    "pl": -102.280655,
    "pvp": 3.05549264,
    "pebit": -69.0404358,
    "pfco": -575.655,
    "psr": 37.05672,
    "pAtivos": 1.93178475,
    "pCapGiro": 61.73333,
    "pAtivCLiq": -6.584776,
    "divYeld": 0.00292765256,
    "evebit": -81.73683,
    "valordaFirma": 5473261570,
    "valordeMercado": 4623085570,
    "fci": 36996000,
    "dbPl": 0,
    "vpa": 4.231724,
    "margBruta": 0.7335941,
    "capex": 25455000,
    "margLiq": -0.36230433,
    "capexLL": -0.5631637,
    "giroAtivos": 0.0521304831,
    "fcf": -44586000,
    "caixaLivre": 0.8184956,
    "fcl": -441000,
    "payout": -0.185044244,
    "lpa": -0.126416877,
    "margEbit": -0.5367394,
    "roic": 0,
    "ebitAtivo": -0.0279804841,
    "fco": -8031000,
    "dpa": 0.0124718,
    "liqCorrent": 1.72599661,
    "divBrPatrim": 0.137934789,
    "capexFco": -3.16959286,
    "fct": 0,
    "ativoCirculante": 178040000,
    "fciLL": 0.8184956,
    "capexDetails": 0,
    "roe": -0.0298736114,
    "roa": -0.0188870989,
    "dlpl": 0.118139565,
    "payoutDetails": 0,
    "ebit": -66962000,
    "lucroLiquido": -45200000,
    "receitaLiquida": 124757000
  },
  {
    "year": 2010,
    "quarter": 3,
    "cresRec": 0,
    "divBruta": 0,
    "data": "09/30/2010 00:00:00",
    "qntAcoes": 357547200,
    "cotacao": 8.81,
    "pl": 515.117859,
    "pvp": 0,
    "pebit": 324.924622,
    "pfco": 430.169,
    "psr": 51.1881981,
    "pAtivos": 0,
    "pCapGiro": 0,
    "pAtivCLiq": 0,
    "divYeld": 0.00141564128,
    "evebit": 0,
    "valordaFirma": 0,
    "valordeMercado": 6249925000,
    "fci": 17779000,
    "dbPl": 0,
    "vpa": 0,
    "margBruta": 0.639475167,
    "capex": 21611000,
    "margLiq": 0.09937181,
    "capexLL": 1.78117526,
    "giroAtivos": 0,
    "fcf": -1778000,
    "caixaLivre": -1.4653424,
    "fcl": -1472000,
    "payout": 0,
    "lpa": 0.03393398,
    "margEbit": 0.157538682,
    "roic": 0,
    "ebitAtivo": 0,
    "fco": 14529000,
    "dpa": 0.0124718,
    "liqCorrent": 0,
    "divBrPatrim": 0,
    "capexFco": 1.48743892,
    "fct": 0,
    "ativoCirculante": 0,
    "fciLL": -1.4653424,
    "capexDetails": 0,
    "roe": 0,
    "roa": 0,
    "dlpl": 0,
    "payoutDetails": 0,
    "ebit": 19235000,
    "lucroLiquido": 12133000,
    "receitaLiquida": 122097000
  },
  {
    "year": 2010,
    "quarter": 2,
    "cresRec": 0,
    "divBruta": 0,
    "data": "06/30/2010 00:00:00",
    "qntAcoes": 357547200,
    "cotacao": 8.81,
    "pl": 359.097076,
    "pvp": 0,
    "pebit": 201.66153,
    "pfco": 420.372437,
    "psr": 40.5306358,
    "pAtivos": 0,
    "pCapGiro": 0,
    "pAtivCLiq": 0,
    "divYeld": 0.00141564128,
    "evebit": 0,
    "valordaFirma": 0,
    "valordeMercado": 4887670270,
    "fci": 16590000,
    "dbPl": 0,
    "vpa": 0,
    "margBruta": 0.6440311,
    "capex": 14570000,
    "margLiq": 0.112868182,
    "capexLL": 1.0704577,
    "giroAtivos": 0,
    "fcf": -5813000,
    "caixaLivre": -1.21886706,
    "fcl": 850000,
    "payout": 0,
    "lpa": 0.0380677,
    "margEbit": 0.20098348,
    "roic": 0,
    "ebitAtivo": 0,
    "fco": 11627000,
    "dpa": 0.0124718,
    "liqCorrent": 0,
    "divBrPatrim": 0,
    "capexFco": 1.2531178,
    "fct": 0,
    "ativoCirculante": 0,
    "fciLL": -1.21886706,
    "capexDetails": 0,
    "roe": 0,
    "roa": 0,
    "dlpl": 0,
    "payoutDetails": 0,
    "ebit": 24237000,
    "lucroLiquido": 13611000,
    "receitaLiquida": 120592000
  },
  {
    "year": 2010,
    "quarter": 1,
    "cresRec": 0,
    "divBruta": 0,
    "data": "03/31/2010 00:00:00",
    "qntAcoes": 357547200,
    "cotacao": 8.81,
    "pl": 612.5668,
    "pvp": 0,
    "pebit": 436.009857,
    "pfco": 282.9987,
    "psr": 40.1979637,
    "pAtivos": 0,
    "pCapGiro": 0,
    "pAtivCLiq": 0,
    "divYeld": 0.0008393337,
    "evebit": 0,
    "valordaFirma": 0,
    "valordeMercado": 4887670270,
    "fci": 15878000,
    "dbPl": 0,
    "vpa": 0,
    "margBruta": 0.663796365,
    "capex": 21628000,
    "margLiq": 0.06562217,
    "capexLL": 2.7106154,
    "giroAtivos": 0,
    "fcf": -701000,
    "caixaLivre": -1.98997366,
    "fcl": 2094000,
    "payout": 0,
    "lpa": 0.0223159343,
    "margEbit": 0.09219508,
    "roic": 0,
    "ebitAtivo": 0,
    "fco": 17271000,
    "dpa": 0.00739453,
    "liqCorrent": 0,
    "divBrPatrim": 0,
    "capexFco": 1.25227261,
    "fct": 0,
    "ativoCirculante": 0,
    "fciLL": -1.98997366,
    "capexDetails": 0,
    "roe": 0,
    "roa": 0,
    "dlpl": 0,
    "payoutDetails": 0,
    "ebit": 11210000,
    "lucroLiquido": 7979000,
    "receitaLiquida": 121590000
  },
  {
    "year": 2009,
    "quarter": 4,
    "cresRec": 0,
    "divBruta": 223476000,
    "data": "12/31/2009 00:00:00",
    "qntAcoes": 357547200,
    "cotacao": 8.81,
    "pl": 0,
    "pvp": 3.850483,
    "pebit": 0,
    "pfco": 0,
    "psr": 0,
    "pAtivos": 2.57521844,
    "pCapGiro": 130.3648,
    "pAtivCLiq": -9.95918,
    "divYeld": 0.0008393337,
    "evebit": 0,
    "valordaFirma": 6633320000,
    "valordeMercado": 5899529000,
    "fci": 0,
    "dbPl": 0,
    "vpa": 4.28517675,
    "margBruta": 0,
    "capex": 0,
    "margLiq": 0,
    "capexLL": 0,
    "giroAtivos": 0,
    "fcf": 0,
    "caixaLivre": 0,
    "fcl": 0,
    "payout": 0,
    "lpa": 0,
    "margEbit": 0,
    "roic": 0,
    "ebitAtivo": 0,
    "fco": 0,
    "dpa": 0.00739453,
    "liqCorrent": 1.37366962,
    "divBrPatrim": 0.1458575,
    "capexFco": 0,
    "fct": 0,
    "ativoCirculante": 166361000,
    "fciLL": 0,
    "capexDetails": 0,
    "roe": 0,
    "roa": 0,
    "dlpl": 0.1295791,
    "payoutDetails": 0,
    "ebit": 0,
    "lucroLiquido": 0,
    "receitaLiquida": 0
  },
  {
    "year": 2008,
    "quarter": 4,
    "cresRec": 0,
    "divBruta": 131026000,
    "data": "12/31/2008 00:00:00",
    "qntAcoes": 357547200,
    "cotacao": 9.79,
    "pl": 0,
    "pvp": 8.844458,
    "pebit": 0,
    "pfco": 0,
    "psr": 0,
    "pAtivos": 5.99568939,
    "pCapGiro": 3315.78564,
    "pAtivCLiq": -25.7811546,
    "divYeld": 0.000246608775,
    "evebit": 0,
    "valordaFirma": 9131917000,
    "valordeMercado": 8674095000,
    "fci": 0,
    "dbPl": 0,
    "vpa": 2.74296069,
    "margBruta": 0,
    "capex": 0,
    "margLiq": 0,
    "capexLL": 0,
    "giroAtivos": 0,
    "fcf": 0,
    "caixaLivre": 0,
    "fcl": 0,
    "payout": 0,
    "lpa": 0,
    "margEbit": 0,
    "roic": 0,
    "ebitAtivo": 0,
    "fco": 0,
    "dpa": 0.0024143,
    "liqCorrent": 1.02061188,
    "divBrPatrim": 0.133599386,
    "capexFco": 0,
    "fct": 0,
    "ativoCirculante": 129533000,
    "fciLL": 0,
    "capexDetails": 0,
    "roe": 0,
    "roa": 0,
    "dlpl": 0.125277087,
    "payoutDetails": 0,
    "ebit": 0,
    "lucroLiquido": 0,
    "receitaLiquida": 0
  }
]